README.rst
setup.py
CommonPack/CommonCaller.py
CommonPack/__init__.py
dadard_apis_common_pack.egg-info/PKG-INFO
dadard_apis_common_pack.egg-info/SOURCES.txt
dadard_apis_common_pack.egg-info/dependency_links.txt
dadard_apis_common_pack.egg-info/requires.txt
dadard_apis_common_pack.egg-info/top_level.txt