Metadata-Version: 1.1
Name: dadard-apis-common-pack
Version: 1.7
Summary: package to interact with the Main API of dadard.fr
Home-page: http://dadard.fr:8010/dadard/DadardApisCommonPack.git
Author: Florian Charpentier
Author-email: florian.charpentier@epita.fr
License: WTFPL
Platform: UNKNOWN
Classifier: Intended Audience :: Developers
Classifier: License :: Freeware
Classifier: Operating System :: OS Independent
Classifier: Programming Language :: Python
Classifier: Programming Language :: Python :: 3.6
